capibara/__init__.py
capibara/main.py
capibara/optimization.py
capibara/py.typed
capibara/version.py
capibara/config/__init__.py
capibara/config/config_manager.py
capibara/config/config_types.py
capibara/config/config_validators.py
capibara/config/distribution_config.py
capibara/config/model_config.py
capibara/config/paths.py
capibara/config/quantum_config.py
capibara/config/scaling_config.py
capibara/config/schemas.py
capibara/config/settings.py
capibara/config/tpu_config.py
capibara/config/training_config.py
capibara/core/__init__.py
capibara/core/config.py
capibara/core/inference.py
capibara/core/model.py
capibara/core/modular_model.py
capibara/core/optimizer.py
capibara/core/tokenizer.py
capibara/data/__init__.py
capibara/data/data_loader.py
capibara/data/data_processing.py
capibara/data/dataset.py
capibara/data/dataset_registry.py
capibara/data/jax_data_processing.py
capibara/encoders/__init__.py
capibara/encoders/capibara_tts.py
capibara/encoders/combiner.py
capibara/encoders/video_encoder.py
capibara/encoders/vision_capi.py
capibara/interfaces/__init__.py
capibara/interfaces/ilayer.py
capibara/interfaces/ilayers.py
capibara/interfaces/imodules.py
capibara/interfaces/isub_models.py
capibara/layers/__init__.py
capibara/layers/base.py
capibara/layers/capibara_layer.py
capibara/layers/conv1d_block.py
capibara/layers/embedding.py
capibara/layers/meta_la.py
capibara/layers/neuro_adaptive.py
capibara/layers/neurogenesis.py
capibara/layers/quantumL.py
capibara/layers/self_attention.py
capibara/layers/stack.py
capibara/mcp/__init__.py
capibara/mcp/auth.py
capibara/mcp/auth_routes.py
capibara/mcp/base.py
capibara/mcp/bias_scanner.py
capibara/mcp/model_control/__init__.py
capibara/mcp/model_control/model_router.py
capibara/mcp/model_control/resource_manager.py
capibara/mcp/model_control/version_manager.py
capibara/mcp/monitoring/__init__.py
capibara/mcp/monitoring/health_check.py
capibara/mcp/monitoring/metrics.py
capibara/mcp/protocol/__init__.py
capibara-2.1.8.dist-info/licenses/LICENSE
capibara-2.1.8.dist-info/licenses/LICENSE.en
capibara-2.1.8.dist-info/METADATA
capibara-2.1.8.dist-info/WHEEL
capibara-2.1.8.dist-info/entry_points.txt
capibara-2.1.8.dist-info/top_level.txt
capibara-2.1.8.dist-info/RECORD
