Metadata-Version: 2.4
Name: capibara
Version: 2.1.8
Summary: Modelo de lenguaje avanzado basado en Mamba SSM
Home-page: https://www.anachroni.co
Author: Anachroni s.coop
Author-email: "Anachroni s.coop" <info@anachroni.com>
License: LICENCIA DUAL CAPIBARA-GPT
Project-URL: Homepage, https://www.anachroni.co
Project-URL: Documentation, https://capibara.readthedocs.io/en/latest/
Project-URL: Repository, https://github.com/anachroni-io/capibara-gpt.git
Project-URL: Bug Tracker, https://github.com/anachroni-io/capibara-gpt/issues
Project-URL: Discord, https://discord.gg/capibara-gpt
Keywords: AI,NLP,LLM,Mamba,SSM
Classifier: Development Status :: 5 - Production/Stable
Classifier: Intended Audience :: Science/Research
Classifier: License :: OSI Approved :: MIT License
Classifier: License :: Other/Proprietary License
Classifier: Programming Language :: Python :: 3
Classifier: Programming Language :: Python :: 3.8
Classifier: Programming Language :: Python :: 3.9
Classifier: Programming Language :: Python :: 3.10
Classifier: Programming Language :: Python :: 3.11
Classifier: Topic :: Scientific/Engineering :: Artificial Intelligence
Requires-Python: >=3.8
License-File: LICENSE
License-File: LICENSE.en
Requires-Dist: torch>=2.0.0
Requires-Dist: transformers>=4.30.0
Requires-Dist: numpy>=1.24.0
Requires-Dist: tqdm>=4.65.0
Requires-Dist: datasets>=2.12.0
Requires-Dist: accelerate>=0.20.0
Requires-Dist: safetensors>=0.3.1
Requires-Dist: einops>=0.6.1
Requires-Dist: mamba-ssm>=1.0.0
Provides-Extra: training
Requires-Dist: wandb>=0.15.0; extra == "training"
Requires-Dist: tensorboard>=2.13.0; extra == "training"
Requires-Dist: pytorch-lightning>=2.0.0; extra == "training"
Provides-Extra: quantization
Requires-Dist: bitsandbytes>=0.41.0; extra == "quantization"
Requires-Dist: optimum>=1.12.0; extra == "quantization"
Provides-Extra: monitoring
Requires-Dist: psutil>=5.9.0; extra == "monitoring"
Requires-Dist: prometheus-client>=0.17.0; extra == "monitoring"
Provides-Extra: all
Requires-Dist: capibara-gpt[training]; extra == "all"
Requires-Dist: capibara-gpt[quantization]; extra == "all"
Requires-Dist: capibara-gpt[monitoring]; extra == "all"
Dynamic: author
Dynamic: home-page
Dynamic: license-file
Dynamic: requires-python
